cyclereward/__init__.py
cyclereward/config.py
cyclereward/model.py
cyclereward/blip/__init__.py
cyclereward/blip/blip.py
cyclereward/blip/blip_pretrain.py
cyclereward/blip/med.py
cyclereward/blip/vit.py
cyclereward-0.1.7.dist-info/LICENSE
cyclereward-0.1.7.dist-info/METADATA
cyclereward-0.1.7.dist-info/WHEEL
cyclereward-0.1.7.dist-info/top_level.txt
cyclereward-0.1.7.dist-info/RECORD
