Metadata-Version: 2.1
Name: cyclereward
Version: 0.1.7
Summary: Image-text alignment metric trained on cycle consistency preferences
Home-page: https://github.com/hjbahng/cyclereward
Author: Hyojin Bahng
License: MIT
Classifier: Programming Language :: Python :: 3
Classifier: License :: OSI Approved :: MIT License
Classifier: Operating System :: OS Independent
Requires-Python: >=3.9
License-File: LICENSE
Requires-Dist: sentencepiece
Requires-Dist: six
Requires-Dist: sniffio
Requires-Dist: submitit
Requires-Dist: sympy
Requires-Dist: tenacity
Requires-Dist: tensorboardX
Requires-Dist: threadpoolctl
Requires-Dist: tiktoken
Requires-Dist: timm
Requires-Dist: tokenizers (>=0.21.1)
Requires-Dist: torch (>=2.6.0)
Requires-Dist: torchvision (>=0.21.0)
Requires-Dist: tqdm
Requires-Dist: transformers
Requires-Dist: triton
Requires-Dist: trl
Requires-Dist: fairscale
